dffml_model_tensorflow_hub/__init__.py
dffml_model_tensorflow_hub/text_classifier.py
dffml_model_tensorflow_hub/tfhub_models.py
dffml_model_tensorflow_hub/tfhub_utils.py
dffml_model_tensorflow_hub/version.py
tests/__init__.py
tests/test_model.py
tests/test_tfhub_integration.py
dffml_model_tensorflow_hub-0.1.0.post0.dist-info/LICENSE
dffml_model_tensorflow_hub-0.1.0.post0.dist-info/METADATA
dffml_model_tensorflow_hub-0.1.0.post0.dist-info/WHEEL
dffml_model_tensorflow_hub-0.1.0.post0.dist-info/entry_points.txt
dffml_model_tensorflow_hub-0.1.0.post0.dist-info/top_level.txt
dffml_model_tensorflow_hub-0.1.0.post0.dist-info/RECORD
