Metadata-Version: 2.1
Name: dffml-model-tensorflow-hub
Version: 0.1.0.post0
Summary: UNKNOWN
Home-page: https://github.com/intel/dffml/blob/master/model/tensorflow_hub/README.md
Author: Himanshu Tripathi
Author-email: himanshutripathi366@gmail.com
License: MIT
Platform: UNKNOWN
Classifier: Development Status :: 3 - Alpha
Classifier: Intended Audience :: Developers
Classifier: License :: OSI Approved :: MIT License
Classifier: License :: OSI Approved :: Apache Software License
Classifier: Natural Language :: English
Classifier: Operating System :: OS Independent
Classifier: Programming Language :: Python :: 3 :: Only
Classifier: Programming Language :: Python :: 3.7
Classifier: Programming Language :: Python :: Implementation :: CPython
Classifier: Programming Language :: Python :: Implementation :: PyPy
License-File: LICENSE
Requires-Dist: dffml (>=0.4.0)
Requires-Dist: dffml-model-tensorflow (>=0.3.0)
Requires-Dist: tensorflow (>=2.0.0)
Requires-Dist: tensorflow-hub (>=0.6.0)
Requires-Dist: pandas (>=0.25.0)
Requires-Dist: numpy (>=1.19.2)
